{
  "official_warnings": [
    {
      "id": "OFF-WTS-1783994772",
      "code": "WTS",
      "zh_name": "雷暴警告",
      "en_name": "Thunderstorm Warning",
      "issue_time": "2026-07-14T03:45:00+08:00",
      "expire_time": "2026-07-14T11:30:00+08:00",
      "status": "ended",
      "last_action": "UPDATE",
      "last_seen_time": "2026-07-14T10:17:00+08:00",
      "end_time": "2026-07-14T11:30:44.258347+08:00",
      "duration": "7h 45m"
    },
    {
      "id": "OFF-WMSGNL-1784025042",
      "code": "WMSGNL",
      "zh_name": "強烈季候風信號",
      "en_name": "Strong Monsoon Signal",
      "issue_time": "2026-07-14T18:20:00+08:00",
      "expire_time": null,
      "status": "cancelled",
      "end_time": "2026-07-14T21:20:00+08:00",
      "duration": "3h 0m"
    },
    {
      "id": "OFF-WTS-1784077254",
      "code": "WTS",
      "zh_name": "雷暴警告",
      "en_name": "Thunderstorm Warning",
      "issue_time": "2026-07-15T08:50:00+08:00",
      "expire_time": "2026-07-15T19:30:00+08:00",
      "status": "cancelled",
      "last_action": "EXTEND",
      "last_seen_time": "2026-07-15T18:20:00+08:00",
      "end_time": "2026-07-15T19:00:00+08:00",
      "duration": "10h 10m"
    },
    {
      "id": "OFF-WRAIN-1784081729",
      "code": "WRAIN",
      "zh_name": "暴雨警告信號",
      "en_name": "Rainstorm Warning Signal",
      "issue_time": "2026-07-15T10:05:00+08:00",
      "expire_time": null,
      "status": "cancelled",
      "end_time": "2026-07-15T15:25:00+08:00",
      "duration": "5h 20m"
    },
    {
      "id": "OFF-WTS-1784151044",
      "code": "WTS",
      "zh_name": "雷暴警告",
      "en_name": "Thunderstorm Warning",
      "issue_time": "2026-07-16T05:19:00+08:00",
      "expire_time": "2026-07-16T16:30:00+08:00",
      "status": "cancelled",
      "last_action": "EXTEND",
      "last_seen_time": "2026-07-16T14:00:00+08:00",
      "end_time": "2026-07-16T15:50:00+08:00",
      "duration": "10h 31m"
    },
    {
      "id": "OFF-WRAIN-1784161843",
      "code": "WRAIN",
      "zh_name": "暴雨警告信號",
      "en_name": "Rainstorm Warning Signal",
      "issue_time": "2026-07-16T07:40:00+08:00",
      "expire_time": null,
      "status": "replaced",
      "end_time": "2026-07-16T09:25:00+08:00",
      "duration": "1h 45m"
    },
    {
      "id": "OFF-WRAIN-1784165447",
      "code": "WRAIN",
      "zh_name": "暴雨警告信號",
      "en_name": "Rainstorm Warning Signal",
      "issue_time": "2026-07-16T09:25:00+08:00",
      "expire_time": null,
      "status": "cancelled",
      "end_time": "2026-07-16T10:20:00+08:00",
      "duration": "0h 55m"
    },
    {
      "id": "OFF-WTS-1784207736",
      "code": "WTS",
      "zh_name": "雷暴警告",
      "en_name": "Thunderstorm Warning",
      "issue_time": "2026-07-16T21:00:00+08:00",
      "expire_time": "2026-07-17T03:30:00+08:00",
      "status": "ended",
      "last_action": "UPDATE",
      "last_seen_time": "2026-07-17T00:40:00+08:00",
      "end_time": "2026-07-17T03:30:38.366083+08:00",
      "duration": "6h 30m"
    },
    {
      "id": "OFF-WRAIN-1784220332",
      "code": "WRAIN",
      "zh_name": "暴雨警告信號",
      "en_name": "Rainstorm Warning Signal",
      "issue_time": "2026-07-17T00:25:00+08:00",
      "expire_time": null,
      "status": "cancelled",
      "end_time": "2026-07-17T02:15:00+08:00",
      "duration": "1h 50m"
    },
    {
      "id": "OFF-WTS-1784231132",
      "code": "WTS",
      "zh_name": "雷暴警告",
      "en_name": "Thunderstorm Warning",
      "issue_time": "2026-07-17T03:42:00+08:00",
      "expire_time": "2026-07-17T17:00:00+08:00",
      "status": "ended",
      "last_action": "EXTEND",
      "last_seen_time": "2026-07-17T15:55:00+08:00",
      "end_time": "2026-07-17T17:00:37.673351+08:00",
      "duration": "13h 18m"
    },
    {
      "id": "OFF-WRAIN-1784258126",
      "code": "WRAIN",
      "zh_name": "暴雨警告信號",
      "en_name": "Rainstorm Warning Signal",
      "issue_time": "2026-07-17T09:50:00+08:00",
      "expire_time": null,
      "status": "cancelled",
      "end_time": "2026-07-17T13:00:00+08:00",
      "duration": "3h 10m"
    },
    {
      "id": "OFF-WTS-1784313930",
      "code": "WTS",
      "zh_name": "雷暴警告",
      "en_name": "Thunderstorm Warning",
      "issue_time": "2026-07-18T02:35:00+08:00",
      "expire_time": "2026-07-18T07:30:00+08:00",
      "status": "replaced",
      "last_action": "EXTEND",
      "last_seen_time": "2026-07-18T05:40:00+08:00",
      "end_time": "2026-07-18T08:55:00+08:00",
      "duration": "6h 20m"
    },
    {
      "id": "OFF-WRAIN-1784320243",
      "code": "WRAIN",
      "zh_name": "暴雨警告信號",
      "en_name": "Rainstorm Warning Signal",
      "issue_time": "2026-07-18T04:20:00+08:00",
      "expire_time": null,
      "status": "ended",
      "end_time": "2026-07-18T09:15:30.589804+08:00",
      "duration": "4h 55m"
    },
    {
      "id": "OFF-WTS-1784337330",
      "code": "WTS",
      "zh_name": "雷暴警告",
      "en_name": "Thunderstorm Warning",
      "issue_time": "2026-07-18T08:55:00+08:00",
      "expire_time": "2026-07-18T13:00:00+08:00",
      "status": "cancelled",
      "last_action": "EXTEND",
      "last_seen_time": "2026-07-18T10:30:00+08:00",
      "end_time": "2026-07-18T13:15:00+08:00",
      "duration": "4h 20m"
    },
    {
      "id": "OFF-WTS-1784361640",
      "code": "WTS",
      "zh_name": "雷暴警告",
      "en_name": "Thunderstorm Warning",
      "issue_time": "2026-07-18T14:20:00+08:00",
      "expire_time": "2026-07-18T18:00:00+08:00",
      "status": "cancelled",
      "last_action": "EXTEND",
      "last_seen_time": "2026-07-18T16:10:00+08:00",
      "end_time": "2026-07-18T17:10:00+08:00",
      "duration": "2h 50m"
    },
    {
      "id": "OFF-WTS-1784430926",
      "code": "WTS",
      "zh_name": "雷暴警告",
      "en_name": "Thunderstorm Warning",
      "issue_time": "2026-07-19T09:25:00+08:00",
      "expire_time": "2026-07-19T12:30:00+08:00",
      "status": "cancelled",
      "last_action": "EXTEND",
      "last_seen_time": "2026-07-19T11:25:00+08:00",
      "end_time": "2026-07-19T12:00:00+08:00",
      "duration": "2h 35m"
    },
    {
      "id": "OFF-WTS-1784449834",
      "code": "WTS",
      "zh_name": "雷暴警告",
      "en_name": "Thunderstorm Warning",
      "issue_time": "2026-07-19T16:21:00+08:00",
      "expire_time": "2026-07-19T18:30:00+08:00",
      "status": "cancelled",
      "end_time": "2026-07-19T18:00:00+08:00",
      "duration": "1h 39m"
    },
    {
      "id": "OFF-WTS-1784495738",
      "code": "WTS",
      "zh_name": "雷暴警告",
      "en_name": "Thunderstorm Warning",
      "issue_time": "2026-07-20T05:10:00+08:00",
      "expire_time": "2026-07-20T16:30:00+08:00",
      "status": "cancelled",
      "last_action": "EXTEND",
      "last_seen_time": "2026-07-20T15:25:00+08:00",
      "end_time": "2026-07-20T16:00:00+08:00",
      "duration": "10h 50m"
    },
    {
      "id": "OFF-WRAIN-1784502926",
      "code": "WRAIN",
      "zh_name": "暴雨警告信號",
      "en_name": "Rainstorm Warning Signal",
      "issue_time": "2026-07-20T07:10:00+08:00",
      "expire_time": null,
      "status": "replaced",
      "end_time": "2026-07-20T09:30:00+08:00",
      "duration": "2h 20m"
    },
    {
      "id": "OFF-WFNTSA-1784511043",
      "code": "WFNTSA",
      "zh_name": "新界北部水浸特別報告",
      "en_name": "Special Announcement on Flooding in Northern New Territories",
      "issue_time": "2026-07-20T08:25:00+08:00",
      "expire_time": null,
      "status": "cancelled",
      "end_time": "2026-07-20T12:30:00+08:00",
      "duration": "4h 5m"
    },
    {
      "id": "OFF-WRAIN-1784511043",
      "code": "WRAIN",
      "zh_name": "暴雨警告信號",
      "en_name": "Rainstorm Warning Signal",
      "issue_time": "2026-07-20T09:30:00+08:00",
      "expire_time": null,
      "status": "cancelled",
      "end_time": "2026-07-20T14:10:00+08:00",
      "duration": "4h 40m"
    },
    {
      "id": "OFF-WTS-1784602840",
      "code": "WTS",
      "zh_name": "雷暴警告",
      "en_name": "Thunderstorm Warning",
      "issue_time": "2026-07-21T10:30:00+08:00",
      "expire_time": "2026-07-21T15:30:00+08:00",
      "status": "cancelled",
      "last_action": "EXTEND",
      "last_seen_time": "2026-07-21T12:00:00+08:00",
      "end_time": "2026-07-21T14:45:00+08:00",
      "duration": "4h 15m"
    }
  ],
  "custom_warnings": [
    {
      "id": "CUST-1783994772",
      "code": "Blue Rainstorm Warning",
      "zh_name": "藍色暴雨警告信號",
      "en_name": "Blue Rainstorm Warning",
      "issue_time": "2026-07-14T10:06:12.847668+08:00",
      "expire_time": "2026-07-14T15:00:00+08:00",
      "status": "expired",
      "end_time": "2026-07-14T15:00:00+08:00",
      "duration": "4h 53m"
    },
    {
      "id": "CUST-1784040245",
      "code": "White Rainstorm Watch",
      "zh_name": "白色暴雨戒備信號",
      "en_name": "White Rainstorm Watch",
      "issue_time": "2026-07-14T22:44:05.553402+08:00",
      "expire_time": null,
      "status": "cancelled",
      "end_time": "2026-07-15T09:49:44.367616+08:00",
      "duration": "11h 5m"
    },
    {
      "id": "CUST-1784080087",
      "code": "Blue Rainstorm Warning",
      "zh_name": "藍色暴雨警告信號",
      "en_name": "Blue Rainstorm Warning",
      "issue_time": "2026-07-15T09:48:07.827583+08:00",
      "expire_time": "2026-07-15T12:00:00+08:00",
      "status": "cancelled",
      "end_time": "2026-07-15T10:20:16.415735+08:00",
      "duration": "0h 32m"
    },
    {
      "id": "CUST-1784095303",
      "code": "Red Rainstorm Watch",
      "zh_name": "紅色暴雨戒備信號",
      "en_name": "Red Rainstorm Watch",
      "issue_time": "2026-07-15T14:01:43.147352+08:00",
      "expire_time": null,
      "status": "cancelled",
      "end_time": "2026-07-15T15:38:58.221449+08:00",
      "duration": "1h 37m"
    }
  ],
  "mesoscale_discussions": [
    {
      "id": "20260722-01",
      "issue_time": "2026-07-22T05:00:38.225841+08:00",
      "status": "active",
      "updates": [
        {
          "time": "2026-07-22T05:00:38.225841+08:00",
          "coords": [
            [
              25.1218,
              109.1377
            ],
            [
              25.2411,
              109.2475
            ],
            [
              25.3007,
              109.3134
            ],
            [
              25.5591,
              109.7749
            ],
            [
              25.5789,
              109.9946
            ],
            [
              25.5591,
              110.1484
            ],
            [
              25.4994,
              110.2143
            ],
            [
              25.4796,
              110.2143
            ],
            [
              25.3603,
              110.1484
            ],
            [
              24.9827,
              109.3574
            ],
            [
              24.9827,
              109.3134
            ],
            [
              25.1019,
              109.1377
            ]
          ],
          "text": "A mesoscale convective area is developing over Hong Kong with estimated rainfall intensity around 42 mm/h. The cell appears organised enough to warrant close monitoring for nearby coastal and inland impacts.",
          "center": [
            25.3301,
            109.6562
          ],
          "movement": "N/A",
          "size": "30 km",
          "intensity": "42mm/h",
          "severity": "S3"
        }
      ]
    },
    {
      "id": "20260722-02",
      "issue_time": "2026-07-22T05:00:38.225841+08:00",
      "status": "active",
      "updates": [
        {
          "time": "2026-07-22T05:00:38.225841+08:00",
          "coords": [
            [
              25.9367,
              109.8628
            ],
            [
              26.0162,
              109.8847
            ],
            [
              26.0758,
              109.9506
            ],
            [
              26.0957,
              109.9946
            ],
            [
              26.1156,
              110.0825
            ],
            [
              26.1354,
              110.1923
            ],
            [
              26.1354,
              110.4121
            ],
            [
              26.0361,
              110.5219
            ],
            [
              25.9963,
              110.5219
            ],
            [
              25.7578,
              110.456
            ],
            [
              25.6783,
              110.4121
            ],
            [
              25.8969,
              109.8628
            ]
          ],
          "text": "A mesoscale convective area is developing over Hong Kong with estimated rainfall intensity around 42 mm/h. The cell appears organised enough to warrant close monitoring for nearby coastal and inland impacts.",
          "center": [
            25.9785,
            110.2067
          ],
          "movement": "N/A",
          "size": "26 km",
          "intensity": "42mm/h",
          "severity": "S3"
        }
      ]
    },
    {
      "id": "20260722-03",
      "issue_time": "2026-07-22T05:00:38.225841+08:00",
      "status": "active",
      "updates": [
        {
          "time": "2026-07-22T05:00:38.225841+08:00",
          "coords": [
            [
              21.5641,
              111.247
            ],
            [
              21.7231,
              111.3349
            ],
            [
              21.7828,
              111.3789
            ],
            [
              21.8225,
              111.5107
            ],
            [
              21.8026,
              111.5766
            ],
            [
              21.7629,
              111.6865
            ],
            [
              21.6834,
              111.7304
            ],
            [
              21.6039,
              111.7524
            ],
            [
              21.3853,
              111.7744
            ],
            [
              21.3256,
              111.7744
            ],
            [
              21.3256,
              111.7524
            ],
            [
              21.3654,
              111.5107
            ],
            [
              21.4051,
              111.4008
            ],
            [
              21.5045,
              111.269
            ],
            [
              21.5244,
              111.247
            ]
          ],
          "text": "A mesoscale convective area is developing over Hong Kong with estimated rainfall intensity around 42 mm/h. The cell appears organised enough to warrant close monitoring for nearby coastal and inland impacts.",
          "center": [
            21.5779,
            111.5296
          ],
          "movement": "N/A",
          "size": "24 km",
          "intensity": "42mm/h",
          "severity": "S3"
        }
      ]
    },
    {
      "id": "20260722-04",
      "issue_time": "2026-07-22T05:00:38.225841+08:00",
      "status": "active",
      "updates": [
        {
          "time": "2026-07-22T05:00:38.225841+08:00",
          "coords": [
            [
              24.9231,
              108.6103
            ],
            [
              25.0224,
              108.6982
            ],
            [
              25.0423,
              108.7422
            ],
            [
              24.9231,
              109.0278
            ],
            [
              24.9032,
              109.0498
            ],
            [
              24.8833,
              109.0498
            ],
            [
              24.8038,
              109.0278
            ],
            [
              24.7839,
              108.896
            ],
            [
              24.7839,
              108.852
            ],
            [
              24.8038,
              108.7422
            ],
            [
              24.8436,
              108.6323
            ],
            [
              24.8634,
              108.6103
            ]
          ],
          "text": "A mesoscale convective area is developing over Hong Kong with estimated rainfall intensity around 42 mm/h. The cell appears organised enough to warrant close monitoring for nearby coastal and inland impacts.",
          "center": [
            24.8879,
            108.8046
          ],
          "movement": "N/A",
          "size": "17 km",
          "intensity": "42mm/h",
          "severity": "S3"
        }
      ]
    },
    {
      "id": "20260722-05",
      "issue_time": "2026-07-22T05:00:38.225841+08:00",
      "status": "active",
      "updates": [
        {
          "time": "2026-07-22T05:00:38.225841+08:00",
          "coords": [
            [
              25.6584,
              109.7968
            ],
            [
              25.7777,
              110.1264
            ],
            [
              25.7777,
              110.1704
            ],
            [
              25.7181,
              110.1923
            ],
            [
              25.6783,
              110.1923
            ],
            [
              25.6386,
              110.1704
            ],
            [
              25.6187,
              110.1264
            ],
            [
              25.5988,
              110.0605
            ],
            [
              25.5988,
              109.7968
            ]
          ],
          "text": "A mesoscale convective area is developing over Hong Kong with estimated rainfall intensity around 42 mm/h. The cell appears organised enough to warrant close monitoring for nearby coastal and inland impacts.",
          "center": [
            25.6742,
            110.0237
          ],
          "movement": "N/A",
          "size": "14 km",
          "intensity": "42mm/h",
          "severity": "S3"
        }
      ]
    },
    {
      "id": "20260722-06",
      "issue_time": "2026-07-22T05:00:38.225841+08:00",
      "status": "active",
      "updates": [
        {
          "time": "2026-07-22T05:00:38.225841+08:00",
          "coords": [
            [
              22.1008,
              111.5766
            ],
            [
              22.1206,
              111.6206
            ],
            [
              22.1206,
              111.7744
            ],
            [
              22.0014,
              111.7964
            ],
            [
              21.9418,
              111.7964
            ],
            [
              21.902,
              111.7744
            ],
            [
              21.8623,
              111.7304
            ],
            [
              21.8424,
              111.6865
            ],
            [
              21.8424,
              111.6645
            ],
            [
              21.8623,
              111.6425
            ],
            [
              22.061,
              111.5766
            ]
          ],
          "text": "A mesoscale convective area is developing over Hong Kong with estimated rainfall intensity around 42 mm/h. The cell appears organised enough to warrant close monitoring for nearby coastal and inland impacts.",
          "center": [
            21.9929,
            111.7024
          ],
          "movement": "N/A",
          "size": "14 km",
          "intensity": "42mm/h",
          "severity": "S3"
        }
      ]
    },
    {
      "id": "20260722-07",
      "issue_time": "2026-07-22T05:00:38.225841+08:00",
      "status": "active",
      "updates": [
        {
          "time": "2026-07-22T05:00:38.225841+08:00",
          "coords": [
            [
              21.0871,
              111.5547
            ],
            [
              21.1468,
              111.5766
            ],
            [
              21.1865,
              111.5986
            ],
            [
              21.2064,
              111.6206
            ],
            [
              21.2859,
              111.7744
            ],
            [
              21.2859,
              111.7964
            ],
            [
              21.2461,
              111.8842
            ],
            [
              21.1666,
              111.8842
            ],
            [
              21.0275,
              111.8403
            ],
            [
              20.9878,
              111.8183
            ],
            [
              20.948,
              111.7744
            ],
            [
              20.9281,
              111.7304
            ],
            [
              20.948,
              111.6865
            ],
            [
              21.0275,
              111.5547
            ]
          ],
          "text": "A mesoscale convective area is developing over Hong Kong with estimated rainfall intensity around 42 mm/h. The cell appears organised enough to warrant close monitoring for nearby coastal and inland impacts.",
          "center": [
            21.1099,
            111.7328
          ],
          "movement": "N/A",
          "size": "14 km",
          "intensity": "42mm/h",
          "severity": "S3"
        }
      ]
    },
    {
      "id": "20260722-08",
      "issue_time": "2026-07-22T05:00:38.225841+08:00",
      "status": "active",
      "updates": [
        {
          "time": "2026-07-22T05:00:38.225841+08:00",
          "coords": [
            [
              21.8026,
              108.9179
            ],
            [
              22.0213,
              109.0278
            ],
            [
              22.0213,
              109.0717
            ],
            [
              22.0014,
              109.0937
            ],
            [
              21.9418,
              109.1157
            ],
            [
              21.8821,
              109.1157
            ],
            [
              21.8026,
              109.0937
            ],
            [
              21.7231,
              108.9619
            ],
            [
              21.7629,
              108.9179
            ]
          ],
          "text": "A mesoscale convective area is developing over Hong Kong with estimated rainfall intensity around 42 mm/h. The cell appears organised enough to warrant close monitoring for nearby coastal and inland impacts.",
          "center": [
            21.8721,
            109.0323
          ],
          "movement": "N/A",
          "size": "12 km",
          "intensity": "42mm/h",
          "severity": "S3"
        }
      ]
    },
    {
      "id": "20260722-09",
      "issue_time": "2026-07-22T05:00:38.225841+08:00",
      "status": "active",
      "updates": [
        {
          "time": "2026-07-22T05:00:38.225841+08:00",
          "coords": [
            [
              26.1752,
              110.5659
            ],
            [
              26.1752,
              110.6098
            ],
            [
              26.1553,
              110.6538
            ],
            [
              26.1156,
              110.6977
            ],
            [
              26.0162,
              110.7197
            ],
            [
              25.9764,
              110.7197
            ],
            [
              25.9367,
              110.6757
            ],
            [
              25.9367,
              110.6098
            ],
            [
              25.9566,
              110.5879
            ],
            [
              26.0361,
              110.5659
            ]
          ],
          "text": "A mesoscale convective area is developing over Hong Kong with estimated rainfall intensity around 42 mm/h. The cell appears organised enough to warrant close monitoring for nearby coastal and inland impacts.",
          "center": [
            26.0481,
            110.6405
          ],
          "movement": "N/A",
          "size": "12 km",
          "intensity": "42mm/h",
          "severity": "S3"
        }
      ]
    },
    {
      "id": "20260722-10",
      "issue_time": "2026-07-22T05:00:38.225841+08:00",
      "status": "active",
      "updates": [
        {
          "time": "2026-07-22T05:00:38.225841+08:00",
          "coords": [
            [
              26.7913,
              110.456
            ],
            [
              26.8311,
              110.478
            ],
            [
              26.8907,
              110.6098
            ],
            [
              26.8907,
              110.6318
            ],
            [
              26.8509,
              110.6538
            ],
            [
              26.8112,
              110.6538
            ],
            [
              26.6721,
              110.5659
            ],
            [
              26.6721,
              110.5439
            ],
            [
              26.6919,
              110.478
            ],
            [
              26.7516,
              110.456
            ]
          ],
          "text": "A mesoscale convective area is developing over Hong Kong with estimated rainfall intensity around 42 mm/h. The cell appears organised enough to warrant close monitoring for nearby coastal and inland impacts.",
          "center": [
            26.7811,
            110.5508
          ],
          "movement": "N/A",
          "size": "12 km",
          "intensity": "42mm/h",
          "severity": "S3"
        }
      ]
    },
    {
      "id": "20260722-11",
      "issue_time": "2026-07-22T05:00:38.225841+08:00",
      "status": "active",
      "updates": [
        {
          "time": "2026-07-22T05:00:38.225841+08:00",
          "coords": [
            [
              23.7305,
              112.873
            ],
            [
              23.8299,
              112.895
            ],
            [
              23.8498,
              112.9389
            ],
            [
              23.7902,
              113.0048
            ],
            [
              23.7107,
              113.0048
            ],
            [
              23.6709,
              112.9609
            ],
            [
              23.6709,
              112.9389
            ],
            [
              23.7107,
              112.873
            ]
          ],
          "text": "A mesoscale convective area is developing over Hong Kong with estimated rainfall intensity around 42 mm/h. The cell appears organised enough to warrant close monitoring for nearby coastal and inland impacts.",
          "center": [
            23.7528,
            112.9438
          ],
          "movement": "N/A",
          "size": "9 km",
          "intensity": "42mm/h",
          "severity": "S3"
        }
      ]
    },
    {
      "id": "20260722-12",
      "issue_time": "2026-07-22T05:00:38.225841+08:00",
      "status": "active",
      "updates": [
        {
          "time": "2026-07-22T05:00:38.225841+08:00",
          "coords": [
            [
              25.8373,
              109.8188
            ],
            [
              25.8572,
              109.9726
            ],
            [
              25.8572,
              109.9946
            ],
            [
              25.7976,
              109.9946
            ],
            [
              25.7379,
              109.9287
            ],
            [
              25.7379,
              109.8628
            ],
            [
              25.8174,
              109.8188
            ]
          ],
          "text": "A mesoscale convective area is developing over Hong Kong with estimated rainfall intensity around 42 mm/h. The cell appears organised enough to warrant close monitoring for nearby coastal and inland impacts.",
          "center": [
            25.7981,
            109.9166
          ],
          "movement": "N/A",
          "size": "9 km",
          "intensity": "42mm/h",
          "severity": "S3"
        }
      ]
    },
    {
      "id": "20260722-13",
      "issue_time": "2026-07-22T05:00:38.225841+08:00",
      "status": "active",
      "updates": [
        {
          "time": "2026-07-22T05:00:38.225841+08:00",
          "coords": [
            [
              24.0088,
              113.2026
            ],
            [
              24.0088,
              113.2905
            ],
            [
              23.969,
              113.2905
            ],
            [
              23.8895,
              113.2465
            ],
            [
              23.8697,
              113.2246
            ],
            [
              23.8697,
              113.2026
            ]
          ],
          "text": "A mesoscale convective area is developing over Hong Kong with estimated rainfall intensity around 42 mm/h. The cell appears organised enough to warrant close monitoring for nearby coastal and inland impacts.",
          "center": [
            23.9477,
            113.2363
          ],
          "movement": "N/A",
          "size": "7 km",
          "intensity": "42mm/h",
          "severity": "S3"
        }
      ]
    },
    {
      "id": "20260722-14",
      "issue_time": "2026-07-22T05:00:38.225841+08:00",
      "status": "active",
      "updates": [
        {
          "time": "2026-07-22T05:00:38.225841+08:00",
          "coords": [
            [
              22.1206,
              111.291
            ],
            [
              22.1405,
              111.313
            ],
            [
              22.1405,
              111.3569
            ],
            [
              22.1008,
              111.4228
            ],
            [
              22.0014,
              111.4228
            ],
            [
              22.0014,
              111.3349
            ],
            [
              22.0809,
              111.291
            ]
          ],
          "text": "A mesoscale convective area is developing over Hong Kong with estimated rainfall intensity around 42 mm/h. The cell appears organised enough to warrant close monitoring for nearby coastal and inland impacts.",
          "center": [
            22.0802,
            111.3545
          ],
          "movement": "N/A",
          "size": "7 km",
          "intensity": "42mm/h",
          "severity": "S3"
        }
      ]
    },
    {
      "id": "20260722-15",
      "issue_time": "2026-07-22T05:00:38.225841+08:00",
      "status": "active",
      "updates": [
        {
          "time": "2026-07-22T05:00:38.225841+08:00",
          "coords": [
            [
              25.0224,
              109.0717
            ],
            [
              25.0622,
              109.1157
            ],
            [
              25.0622,
              109.1596
            ],
            [
              25.0026,
              109.1596
            ],
            [
              24.9827,
              109.1377
            ],
            [
              24.9827,
              109.0717
            ]
          ],
          "text": "A mesoscale convective area is developing over Hong Kong with estimated rainfall intensity around 42 mm/h. The cell appears organised enough to warrant close monitoring for nearby coastal and inland impacts.",
          "center": [
            25.0175,
            109.1179
          ],
          "movement": "N/A",
          "size": "6 km",
          "intensity": "42mm/h",
          "severity": "S3"
        },
        {
          "time": "2026-07-22T05:00:38.225841+08:00",
          "coords": [
            [
              25.0224,
              109.0058
            ],
            [
              25.0224,
              109.0278
            ],
            [
              24.9827,
              109.0278
            ],
            [
              24.9827,
              109.0058
            ]
          ],
          "text": "A mesoscale convective area is developing over Hong Kong with estimated rainfall intensity around 20 mm/h. The cell appears organised enough to warrant close monitoring for nearby coastal and inland impacts.",
          "center": [
            25.0026,
            109.0168
          ],
          "movement": "N/A",
          "size": "3 km",
          "intensity": "20mm/h",
          "severity": "S1"
        }
      ]
    },
    {
      "id": "20260722-16",
      "issue_time": "2026-07-22T05:00:38.225841+08:00",
      "status": "active",
      "updates": [
        {
          "time": "2026-07-22T05:00:38.225841+08:00",
          "coords": [
            [
              26.2547,
              109.9726
            ],
            [
              26.2944,
              109.9946
            ],
            [
              26.2944,
              110.0166
            ],
            [
              26.2746,
              110.0605
            ],
            [
              26.2348,
              110.0605
            ],
            [
              26.2149,
              110.0166
            ],
            [
              26.2149,
              109.9726
            ]
          ],
          "text": "A mesoscale convective area is developing over Hong Kong with estimated rainfall intensity around 42 mm/h. The cell appears organised enough to warrant close monitoring for nearby coastal and inland impacts.",
          "center": [
            26.2516,
            110.0143
          ],
          "movement": "N/A",
          "size": "6 km",
          "intensity": "42mm/h",
          "severity": "S3"
        },
        {
          "time": "2026-07-22T05:00:38.225841+08:00",
          "coords": [
            [
              26.2944,
              110.1045
            ],
            [
              26.3143,
              110.1264
            ],
            [
              26.2944,
              110.1484
            ],
            [
              26.2746,
              110.1484
            ],
            [
              26.2149,
              110.1045
            ]
          ],
          "text": "A mesoscale convective area is developing over Hong Kong with estimated rainfall intensity around 20 mm/h. The cell appears organised enough to warrant close monitoring for nearby coastal and inland impacts.",
          "center": [
            26.271,
            110.1204
          ],
          "movement": "N/A",
          "size": "4 km",
          "intensity": "20mm/h",
          "severity": "S1"
        }
      ]
    },
    {
      "id": "20260722-17",
      "issue_time": "2026-07-22T05:00:38.225841+08:00",
      "status": "active",
      "updates": [
        {
          "time": "2026-07-22T05:00:38.225841+08:00",
          "coords": [
            [
              26.5329,
              110.3242
            ],
            [
              26.6323,
              110.3681
            ],
            [
              26.5926,
              110.3901
            ],
            [
              26.5131,
              110.3901
            ],
            [
              26.4932,
              110.3242
            ]
          ],
          "text": "A mesoscale convective area is developing over Hong Kong with estimated rainfall intensity around 20 mm/h. The cell appears organised enough to warrant close monitoring for nearby coastal and inland impacts.",
          "center": [
            26.5518,
            110.3623
          ],
          "movement": "N/A",
          "size": "6 km",
          "intensity": "20mm/h",
          "severity": "S1"
        },
        {
          "time": "2026-07-22T05:00:38.225841+08:00",
          "coords": [
            [
              26.5926,
              110.456
            ],
            [
              26.5926,
              110.478
            ],
            [
              26.5727,
              110.478
            ],
            [
              26.5727,
              110.456
            ]
          ],
          "text": "A mesoscale convective area is developing over Hong Kong with estimated rainfall intensity around 20 mm/h. The cell appears organised enough to warrant close monitoring for nearby coastal and inland impacts.",
          "center": [
            26.5826,
            110.467
          ],
          "movement": "N/A",
          "size": "3 km",
          "intensity": "20mm/h",
          "severity": "S1"
        }
      ]
    },
    {
      "id": "20260722-18",
      "issue_time": "2026-07-22T05:00:38.225841+08:00",
      "status": "active",
      "updates": [
        {
          "time": "2026-07-22T05:00:38.225841+08:00",
          "coords": [
            [
              21.9219,
              112.5654
            ],
            [
              21.9219,
              112.5874
            ],
            [
              21.8225,
              112.6533
            ],
            [
              21.7828,
              112.6533
            ],
            [
              21.7828,
              112.6093
            ],
            [
              21.8821,
              112.5654
            ]
          ],
          "text": "A mesoscale convective area is developing over Hong Kong with estimated rainfall intensity around 42 mm/h. The cell appears organised enough to warrant close monitoring for nearby coastal and inland impacts.",
          "center": [
            21.8435,
            112.6069
          ],
          "movement": "N/A",
          "size": "6 km",
          "intensity": "42mm/h",
          "severity": "S3"
        }
      ]
    },
    {
      "id": "20260722-19",
      "issue_time": "2026-07-22T05:00:38.225841+08:00",
      "status": "active",
      "updates": [
        {
          "time": "2026-07-22T05:00:38.225841+08:00",
          "coords": [
            [
              22.8163,
              114.6089
            ],
            [
              22.8163,
              114.6528
            ],
            [
              22.7368,
              114.6967
            ],
            [
              22.7169,
              114.6967
            ],
            [
              22.7169,
              114.6748
            ],
            [
              22.7765,
              114.6089
            ]
          ],
          "text": "A mesoscale convective area is developing over Hong Kong with estimated rainfall intensity around 42 mm/h. The cell appears organised enough to warrant close monitoring for nearby coastal and inland impacts.",
          "center": [
            22.7726,
            114.6469
          ],
          "movement": "N/A",
          "size": "5 km",
          "intensity": "42mm/h",
          "severity": "S3"
        }
      ]
    },
    {
      "id": "20260722-20",
      "issue_time": "2026-07-22T05:00:38.225841+08:00",
      "status": "active",
      "updates": [
        {
          "time": "2026-07-22T05:00:38.225841+08:00",
          "coords": [
            [
              22.22,
              109.5112
            ],
            [
              22.2598,
              109.5332
            ],
            [
              22.2399,
              109.5551
            ],
            [
              22.1803,
              109.5551
            ],
            [
              22.1604,
              109.5332
            ],
            [
              22.2002,
              109.5112
            ]
          ],
          "text": "A mesoscale convective area is developing over Hong Kong with estimated rainfall intensity around 20 mm/h. The cell appears organised enough to warrant close monitoring for nearby coastal and inland impacts.",
          "center": [
            22.2101,
            109.5368
          ],
          "movement": "N/A",
          "size": "5 km",
          "intensity": "20mm/h",
          "severity": "S1"
        }
      ]
    },
    {
      "id": "20260722-21",
      "issue_time": "2026-07-22T05:00:38.225841+08:00",
      "status": "active",
      "updates": [
        {
          "time": "2026-07-22T05:00:38.225841+08:00",
          "coords": [
            [
              22.1803,
              111.6425
            ],
            [
              22.2002,
              111.6645
            ],
            [
              22.2002,
              111.7085
            ],
            [
              22.1803,
              111.7304
            ],
            [
              22.1604,
              111.7304
            ],
            [
              22.1604,
              111.6865
            ]
          ],
          "text": "A mesoscale convective area is developing over Hong Kong with estimated rainfall intensity around 42 mm/h. The cell appears organised enough to warrant close monitoring for nearby coastal and inland impacts.",
          "center": [
            22.1803,
            111.6925
          ],
          "movement": "N/A",
          "size": "4 km",
          "intensity": "42mm/h",
          "severity": "S3"
        }
      ]
    },
    {
      "id": "20260722-22",
      "issue_time": "2026-07-22T05:00:38.225841+08:00",
      "status": "active",
      "updates": [
        {
          "time": "2026-07-22T05:00:38.225841+08:00",
          "coords": [
            [
              19.8748,
              111.1811
            ],
            [
              19.7953,
              111.2031
            ],
            [
              19.7356,
              111.2031
            ],
            [
              19.7555,
              111.1811
            ]
          ],
          "text": "A mesoscale convective area is developing over Hong Kong with estimated rainfall intensity around 20 mm/h. The cell appears organised enough to warrant close monitoring for nearby coastal and inland impacts.",
          "center": [
            19.7971,
            111.1891
          ],
          "movement": "N/A",
          "size": "4 km",
          "intensity": "20mm/h",
          "severity": "S1"
        }
      ]
    },
    {
      "id": "20260722-23",
      "issue_time": "2026-07-22T05:00:38.225841+08:00",
      "status": "active",
      "updates": [
        {
          "time": "2026-07-22T05:00:38.225841+08:00",
          "coords": [
            [
              26.0361,
              110.9174
            ],
            [
              26.0957,
              110.9394
            ],
            [
              26.0957,
              110.9614
            ],
            [
              26.0758,
              110.9834
            ],
            [
              26.0559,
              110.9834
            ],
            [
              26.0162,
              110.9174
            ]
          ],
          "text": "A mesoscale convective area is developing over Hong Kong with estimated rainfall intensity around 20 mm/h. The cell appears organised enough to warrant close monitoring for nearby coastal and inland impacts.",
          "center": [
            26.0639,
            110.9504
          ],
          "movement": "N/A",
          "size": "4 km",
          "intensity": "20mm/h",
          "severity": "S1"
        }
      ]
    },
    {
      "id": "20260722-24",
      "issue_time": "2026-07-22T05:00:38.225841+08:00",
      "status": "active",
      "updates": [
        {
          "time": "2026-07-22T05:00:38.225841+08:00",
          "coords": [
            [
              23.5517,
              112.6753
            ],
            [
              23.5715,
              112.6972
            ],
            [
              23.5715,
              112.7192
            ],
            [
              23.5119,
              112.7412
            ],
            [
              23.5119,
              112.6972
            ],
            [
              23.5318,
              112.6753
            ]
          ],
          "text": "A mesoscale convective area is developing over Hong Kong with estimated rainfall intensity around 42 mm/h. The cell appears organised enough to warrant close monitoring for nearby coastal and inland impacts.",
          "center": [
            23.5384,
            112.7021
          ],
          "movement": "N/A",
          "size": "4 km",
          "intensity": "42mm/h",
          "severity": "S3"
        }
      ]
    },
    {
      "id": "20260722-25",
      "issue_time": "2026-07-22T05:00:38.225841+08:00",
      "status": "active",
      "updates": [
        {
          "time": "2026-07-22T05:00:38.225841+08:00",
          "coords": [
            [
              25.0224,
              109.7529
            ],
            [
              25.0423,
              109.7749
            ],
            [
              25.0423,
              109.7968
            ],
            [
              25.0224,
              109.7968
            ],
            [
              24.9827,
              109.7749
            ],
            [
              24.9827,
              109.7529
            ]
          ],
          "text": "A mesoscale convective area is developing over Hong Kong with estimated rainfall intensity around 20 mm/h. The cell appears organised enough to warrant close monitoring for nearby coastal and inland impacts.",
          "center": [
            25.0136,
            109.7724
          ],
          "movement": "N/A",
          "size": "4 km",
          "intensity": "20mm/h",
          "severity": "S1"
        }
      ]
    },
    {
      "id": "20260722-26",
      "issue_time": "2026-07-22T05:00:38.225841+08:00",
      "status": "active",
      "updates": [
        {
          "time": "2026-07-22T05:00:38.225841+08:00",
          "coords": [
            [
              25.2212,
              109.7968
            ],
            [
              25.2212,
              109.8408
            ],
            [
              25.2013,
              109.8408
            ],
            [
              25.1616,
              109.7968
            ]
          ],
          "text": "A mesoscale convective area is developing over Hong Kong with estimated rainfall intensity around 20 mm/h. The cell appears organised enough to warrant close monitoring for nearby coastal and inland impacts.",
          "center": [
            25.2013,
            109.8133
          ],
          "movement": "N/A",
          "size": "4 km",
          "intensity": "20mm/h",
          "severity": "S1"
        }
      ]
    },
    {
      "id": "20260722-27",
      "issue_time": "2026-07-22T05:00:38.225841+08:00",
      "status": "active",
      "updates": [
        {
          "time": "2026-07-22T05:00:38.225841+08:00",
          "coords": [
            [
              22.8759,
              110.3462
            ],
            [
              22.8759,
              110.3681
            ],
            [
              22.8163,
              110.3901
            ],
            [
              22.7964,
              110.3901
            ],
            [
              22.8362,
              110.3462
            ]
          ],
          "text": "A mesoscale convective area is developing over Hong Kong with estimated rainfall intensity around 20 mm/h. The cell appears organised enough to warrant close monitoring for nearby coastal and inland impacts.",
          "center": [
            22.8436,
            110.3654
          ],
          "movement": "N/A",
          "size": "4 km",
          "intensity": "20mm/h",
          "severity": "S1"
        },
        {
          "time": "2026-07-22T05:00:38.225841+08:00",
          "coords": [
            [
              22.8163,
              110.2802
            ],
            [
              22.8362,
              110.3022
            ],
            [
              22.8163,
              110.3022
            ],
            [
              22.7964,
              110.2802
            ]
          ],
          "text": "A mesoscale convective area is developing over Hong Kong with estimated rainfall intensity around 20 mm/h. The cell appears organised enough to warrant close monitoring for nearby coastal and inland impacts.",
          "center": [
            22.8163,
            110.2912
          ],
          "movement": "N/A",
          "size": "3 km",
          "intensity": "20mm/h",
          "severity": "S1"
        }
      ]
    },
    {
      "id": "20260722-28",
      "issue_time": "2026-07-22T05:00:38.225841+08:00",
      "status": "active",
      "updates": [
        {
          "time": "2026-07-22T05:00:38.225841+08:00",
          "coords": [
            [
              25.7578,
              110.2802
            ],
            [
              25.7777,
              110.3022
            ],
            [
              25.7181,
              110.3022
            ],
            [
              25.7181,
              110.2802
            ]
          ],
          "text": "A mesoscale convective area is developing over Hong Kong with estimated rainfall intensity around 20 mm/h. The cell appears organised enough to warrant close monitoring for nearby coastal and inland impacts.",
          "center": [
            25.7436,
            110.2928
          ],
          "movement": "N/A",
          "size": "3 km",
          "intensity": "20mm/h",
          "severity": "S1"
        }
      ]
    },
    {
      "id": "20260722-29",
      "issue_time": "2026-07-22T05:00:38.225841+08:00",
      "status": "active",
      "updates": [
        {
          "time": "2026-07-22T05:00:38.225841+08:00",
          "coords": [
            [
              26.2944,
              110.5
            ],
            [
              26.3143,
              110.5439
            ],
            [
              26.2746,
              110.5439
            ],
            [
              26.2746,
              110.5
            ]
          ],
          "text": "A mesoscale convective area is developing over Hong Kong with estimated rainfall intensity around 20 mm/h. The cell appears organised enough to warrant close monitoring for nearby coastal and inland impacts.",
          "center": [
            26.2888,
            110.5251
          ],
          "movement": "N/A",
          "size": "3 km",
          "intensity": "20mm/h",
          "severity": "S1"
        }
      ]
    },
    {
      "id": "20260722-30",
      "issue_time": "2026-07-22T05:00:38.225841+08:00",
      "status": "active",
      "updates": [
        {
          "time": "2026-07-22T05:00:38.225841+08:00",
          "coords": [
            [
              25.2013,
              108.5444
            ],
            [
              25.2013,
              108.5883
            ],
            [
              25.1814,
              108.5883
            ],
            [
              25.1814,
              108.5444
            ]
          ],
          "text": "A mesoscale convective area is developing over Hong Kong with estimated rainfall intensity around 42 mm/h. The cell appears organised enough to warrant close monitoring for nearby coastal and inland impacts.",
          "center": [
            25.1914,
            108.5664
          ],
          "movement": "N/A",
          "size": "3 km",
          "intensity": "42mm/h",
          "severity": "S3"
        }
      ]
    },
    {
      "id": "20260722-31",
      "issue_time": "2026-07-22T05:00:38.225841+08:00",
      "status": "active",
      "updates": [
        {
          "time": "2026-07-22T05:00:38.225841+08:00",
          "coords": [
            [
              17.2512,
              109.0498
            ],
            [
              17.3109,
              109.0717
            ],
            [
              17.2512,
              109.0937
            ]
          ],
          "text": "A mesoscale convective area is developing over Hong Kong with estimated rainfall intensity around 42 mm/h. The cell appears organised enough to warrant close monitoring for nearby coastal and inland impacts.",
          "center": [
            17.2711,
            109.0717
          ],
          "movement": "N/A",
          "size": "3 km",
          "intensity": "42mm/h",
          "severity": "S3"
        }
      ]
    },
    {
      "id": "20260722-32",
      "issue_time": "2026-07-22T05:00:38.225841+08:00",
      "status": "active",
      "updates": [
        {
          "time": "2026-07-22T05:00:38.225841+08:00",
          "coords": [
            [
              22.0411,
              108.9399
            ],
            [
              22.0411,
              108.9619
            ],
            [
              22.0014,
              108.9619
            ],
            [
              22.0014,
              108.9399
            ]
          ],
          "text": "A mesoscale convective area is developing over Hong Kong with estimated rainfall intensity around 42 mm/h. The cell appears organised enough to warrant close monitoring for nearby coastal and inland impacts.",
          "center": [
            22.0213,
            108.9509
          ],
          "movement": "N/A",
          "size": "3 km",
          "intensity": "42mm/h",
          "severity": "S3"
        }
      ]
    },
    {
      "id": "20260722-33",
      "issue_time": "2026-07-22T05:00:38.225841+08:00",
      "status": "active",
      "updates": [
        {
          "time": "2026-07-22T05:00:38.225841+08:00",
          "coords": [
            [
              22.9157,
              114.5649
            ],
            [
              22.9157,
              114.5869
            ],
            [
              22.8759,
              114.5869
            ],
            [
              22.8759,
              114.5649
            ]
          ],
          "text": "A mesoscale convective area is developing over Hong Kong with estimated rainfall intensity around 20 mm/h. The cell appears organised enough to warrant close monitoring for nearby coastal and inland impacts.",
          "center": [
            22.8958,
            114.5759
          ],
          "movement": "N/A",
          "size": "3 km",
          "intensity": "20mm/h",
          "severity": "S1"
        }
      ]
    },
    {
      "id": "20260722-34",
      "issue_time": "2026-07-22T05:00:38.225841+08:00",
      "status": "active",
      "updates": [
        {
          "time": "2026-07-22T05:00:38.225841+08:00",
          "coords": [
            [
              27.1292,
              118.0805
            ],
            [
              27.1292,
              118.1025
            ],
            [
              27.0894,
              118.1025
            ],
            [
              27.0894,
              118.0805
            ]
          ],
          "text": "A mesoscale convective area is developing over Hong Kong with estimated rainfall intensity around 20 mm/h. The cell appears organised enough to warrant close monitoring for nearby coastal and inland impacts.",
          "center": [
            27.1093,
            118.0915
          ],
          "movement": "N/A",
          "size": "3 km",
          "intensity": "20mm/h",
          "severity": "S1"
        }
      ]
    },
    {
      "id": "20260722-35",
      "issue_time": "2026-07-22T05:00:38.225841+08:00",
      "status": "active",
      "updates": [
        {
          "time": "2026-07-22T05:00:38.225841+08:00",
          "coords": [
            [
              23.8299,
              113.1147
            ],
            [
              23.8299,
              113.1367
            ],
            [
              23.7902,
              113.1367
            ],
            [
              23.7902,
              113.1147
            ]
          ],
          "text": "A mesoscale convective area is developing over Hong Kong with estimated rainfall intensity around 20 mm/h. The cell appears organised enough to warrant close monitoring for nearby coastal and inland impacts.",
          "center": [
            23.81,
            113.1257
          ],
          "movement": "N/A",
          "size": "3 km",
          "intensity": "20mm/h",
          "severity": "S1"
        }
      ]
    },
    {
      "id": "20260722-36",
      "issue_time": "2026-07-22T05:00:38.225841+08:00",
      "status": "active",
      "updates": [
        {
          "time": "2026-07-22T05:00:38.225841+08:00",
          "coords": [
            [
              25.8572,
              110.5219
            ],
            [
              25.8572,
              110.5439
            ],
            [
              25.8174,
              110.5439
            ],
            [
              25.8174,
              110.5219
            ]
          ],
          "text": "A mesoscale convective area is developing over Hong Kong with estimated rainfall intensity around 20 mm/h. The cell appears organised enough to warrant close monitoring for nearby coastal and inland impacts.",
          "center": [
            25.8373,
            110.5329
          ],
          "movement": "N/A",
          "size": "3 km",
          "intensity": "20mm/h",
          "severity": "S1"
        },
        {
          "time": "2026-07-22T05:00:38.225841+08:00",
          "coords": [
            [
              25.8969,
              110.5879
            ],
            [
              25.8572,
              110.6098
            ],
            [
              25.8174,
              110.6098
            ],
            [
              25.8572,
              110.5879
            ]
          ],
          "text": "A mesoscale convective area is developing over Hong Kong with estimated rainfall intensity around 20 mm/h. The cell appears organised enough to warrant close monitoring for nearby coastal and inland impacts.",
          "center": [
            25.8572,
            110.5988
          ],
          "movement": "N/A",
          "size": "3 km",
          "intensity": "20mm/h",
          "severity": "S1"
        }
      ]
    },
    {
      "id": "20260722-37",
      "issue_time": "2026-07-22T05:00:38.225841+08:00",
      "status": "active",
      "updates": [
        {
          "time": "2026-07-22T05:00:38.225841+08:00",
          "coords": [
            [
              26.8509,
              110.9834
            ],
            [
              26.8907,
              111.0053
            ],
            [
              26.8509,
              111.0053
            ],
            [
              26.8112,
              110.9834
            ]
          ],
          "text": "A mesoscale convective area is developing over Hong Kong with estimated rainfall intensity around 20 mm/h. The cell appears organised enough to warrant close monitoring for nearby coastal and inland impacts.",
          "center": [
            26.8509,
            110.9944
          ],
          "movement": "N/A",
          "size": "3 km",
          "intensity": "20mm/h",
          "severity": "S1"
        }
      ]
    },
    {
      "id": "20260722-38",
      "issue_time": "2026-07-22T05:00:38.225841+08:00",
      "status": "active",
      "updates": [
        {
          "time": "2026-07-22T05:00:38.225841+08:00",
          "coords": [
            [
              22.3592,
              115.3779
            ],
            [
              22.3592,
              115.3999
            ],
            [
              22.3194,
              115.3999
            ],
            [
              22.3393,
              115.3779
            ]
          ],
          "text": "A mesoscale convective area is developing over Hong Kong with estimated rainfall intensity around 42 mm/h. The cell appears organised enough to warrant close monitoring for nearby coastal and inland impacts.",
          "center": [
            22.3433,
            115.3911
          ],
          "movement": "N/A",
          "size": "3 km",
          "intensity": "42mm/h",
          "severity": "S3"
        }
      ]
    },
    {
      "id": "20260722-39",
      "issue_time": "2026-07-22T05:00:38.225841+08:00",
      "status": "active",
      "updates": [
        {
          "time": "2026-07-22T05:00:38.225841+08:00",
          "coords": [
            [
              22.0213,
              111.5327
            ],
            [
              22.0213,
              111.5547
            ],
            [
              21.9815,
              111.5547
            ],
            [
              22.0014,
              111.5327
            ]
          ],
          "text": "A mesoscale convective area is developing over Hong Kong with estimated rainfall intensity around 20 mm/h. The cell appears organised enough to warrant close monitoring for nearby coastal and inland impacts.",
          "center": [
            22.0054,
            111.5459
          ],
          "movement": "N/A",
          "size": "3 km",
          "intensity": "20mm/h",
          "severity": "S1"
        },
        {
          "time": "2026-07-22T05:00:38.225841+08:00",
          "coords": [
            [
              21.9418,
              111.5107
            ],
            [
              21.9418,
              111.5327
            ],
            [
              21.9219,
              111.5327
            ],
            [
              21.9219,
              111.5107
            ]
          ],
          "text": "A mesoscale convective area is developing over Hong Kong with estimated rainfall intensity around 20 mm/h. The cell appears organised enough to warrant close monitoring for nearby coastal and inland impacts.",
          "center": [
            21.9318,
            111.5217
          ],
          "movement": "N/A",
          "size": "3 km",
          "intensity": "20mm/h",
          "severity": "S1"
        }
      ]
    },
    {
      "id": "20260722-40",
      "issue_time": "2026-07-22T05:00:38.225841+08:00",
      "status": "active",
      "updates": [
        {
          "time": "2026-07-22T05:00:38.225841+08:00",
          "coords": [
            [
              25.9963,
              111.9721
            ],
            [
              25.9963,
              111.9941
            ],
            [
              25.9764,
              111.9941
            ],
            [
              25.9764,
              111.9721
            ]
          ],
          "text": "A mesoscale convective area is developing over Hong Kong with estimated rainfall intensity around 20 mm/h. The cell appears organised enough to warrant close monitoring for nearby coastal and inland impacts.",
          "center": [
            25.9864,
            111.9831
          ],
          "movement": "N/A",
          "size": "3 km",
          "intensity": "20mm/h",
          "severity": "S1"
        }
      ]
    },
    {
      "id": "20260722-41",
      "issue_time": "2026-07-22T05:00:38.225841+08:00",
      "status": "active",
      "updates": [
        {
          "time": "2026-07-22T05:00:38.225841+08:00",
          "coords": [
            [
              22.4387,
              109.1377
            ],
            [
              22.4387,
              109.1596
            ],
            [
              22.4188,
              109.1596
            ],
            [
              22.4188,
              109.1377
            ]
          ],
          "text": "A mesoscale convective area is developing over Hong Kong with estimated rainfall intensity around 20 mm/h. The cell appears organised enough to warrant close monitoring for nearby coastal and inland impacts.",
          "center": [
            22.4287,
            109.1486
          ],
          "movement": "N/A",
          "size": "3 km",
          "intensity": "20mm/h",
          "severity": "S1"
        }
      ]
    },
    {
      "id": "20260722-42",
      "issue_time": "2026-07-22T05:00:38.225841+08:00",
      "status": "active",
      "updates": [
        {
          "time": "2026-07-22T05:00:38.225841+08:00",
          "coords": [
            [
              25.6982,
              109.7309
            ],
            [
              25.6982,
              109.7529
            ],
            [
              25.6783,
              109.7529
            ],
            [
              25.6783,
              109.7309
            ]
          ],
          "text": "A mesoscale convective area is developing over Hong Kong with estimated rainfall intensity around 20 mm/h. The cell appears organised enough to warrant close monitoring for nearby coastal and inland impacts.",
          "center": [
            25.6882,
            109.7419
          ],
          "movement": "N/A",
          "size": "3 km",
          "intensity": "20mm/h",
          "severity": "S1"
        }
      ]
    },
    {
      "id": "20260722-43",
      "issue_time": "2026-07-22T05:00:38.225841+08:00",
      "status": "active",
      "updates": [
        {
          "time": "2026-07-22T05:00:38.225841+08:00",
          "coords": [
            [
              26.1752,
              110.7636
            ],
            [
              26.1752,
              110.7856
            ],
            [
              26.1553,
              110.7856
            ],
            [
              26.1553,
              110.7636
            ]
          ],
          "text": "A mesoscale convective area is developing over Hong Kong with estimated rainfall intensity around 20 mm/h. The cell appears organised enough to warrant close monitoring for nearby coastal and inland impacts.",
          "center": [
            26.1653,
            110.7746
          ],
          "movement": "N/A",
          "size": "3 km",
          "intensity": "20mm/h",
          "severity": "S1"
        }
      ]
    },
    {
      "id": "20260722-44",
      "issue_time": "2026-07-22T05:00:38.225841+08:00",
      "status": "active",
      "updates": [
        {
          "time": "2026-07-22T05:00:38.225841+08:00",
          "coords": [
            [
              24.0485,
              113.1367
            ],
            [
              24.0485,
              113.1587
            ],
            [
              24.0287,
              113.1587
            ],
            [
              24.0287,
              113.1367
            ]
          ],
          "text": "A mesoscale convective area is developing over Hong Kong with estimated rainfall intensity around 20 mm/h. The cell appears organised enough to warrant close monitoring for nearby coastal and inland impacts.",
          "center": [
            24.0386,
            113.1477
          ],
          "movement": "N/A",
          "size": "3 km",
          "intensity": "20mm/h",
          "severity": "S1"
        }
      ]
    }
  ],
  "announcements": [
    {
      "time": "2026-07-14T10:06:12.847668+08:00",
      "text": "1. Expect heavy rain of about 30mm/h to form over the next 2-3 hours.\n2. About 20mm/h of heavy rain is currently impacting on most parts of Hong Kong."
    },
    {
      "time": "2026-07-14T22:44:05.553402+08:00",
      "text": "1. Expect heavy rain of about 10mm/h to form over the next 2-3 hours.\n2. About 10mm/h of heavy rain is currently impacting on most parts of Hong Kong."
    },
    {
      "time": "2026-07-15T09:48:07.827583+08:00",
      "text": "1. Expect heavy rain of about 30mm/h to form over the next 2-3 hours.\n2. About 20mm/h of heavy rain is currently impacting on most parts of Hong Kong."
    },
    {
      "time": "2026-07-15T14:01:43.147352+08:00",
      "text": "The chance of issuing Red Rainstorm Warning has reached more than 70%, it is very likely that a 50mm/h heavy rain will impact Hong Kong very soon."
    }
  ]
}